daily_utils.py
daily_utils-0.0.3.dist-info/METADATA
daily_utils-0.0.3.dist-info/WHEEL
daily_utils-0.0.3.dist-info/licenses/LICENSE
daily_utils-0.0.3.dist-info/RECORD
