Metadata-Version: 2.3
Name: daily_utils
Version: 0.0.3
Summary: A package for utility functions for data science
Project-URL: Homepage, https://github.com/laiviet/daily_utils
Project-URL: Issues, https://github.com/laiviet/daily_utils/issues
Author-email: Viet Lai <viet.ptit.bn@gmail.com>
License-Expression: MIT
License-File: LICENSE
Keywords: data science,utils
Classifier: License :: OSI Approved :: MIT License
Classifier: Operating System :: OS Independent
Classifier: Programming Language :: Python :: 3
Requires-Python: >=3.8
Provides-Extra: tqdm
Requires-Dist: tqdm; extra == 'tqdm'
